tankersdk/__init__.py
tankersdk-0.1.1.dist-info/WHEEL
tankersdk-0.1.1.dist-info/METADATA
tankersdk-0.1.1.dist-info/RECORD
