Metadata-Version: 2.1
Name: tankersdk
Version: 0.1.1
Summary: Python client for Tanker
Home-page: https://gitlab.com/TankerHQ/sdk-python/
License: Apache 2.0
Author: Tanker team
Author-email: tech@tanker.io
Requires-Python: >=3.7,<4.0
Classifier: License :: Other/Proprietary License
Classifier: Programming Language :: Python :: 3
Classifier: Programming Language :: Python :: 3.7
Classifier: Programming Language :: Python :: 3.8
Classifier: Programming Language :: Python :: 3.9
